[
    {
        "id": "1",
        "nome": "Pura Vida App",
        "username": "puravidaapp",
        "bio": "Usuário padrão",
        "restricao": false,
        "restricao_id": [],
        "ultimo_login": ""
    },
    {
        "id": "2",
        "nome": "Pedro Henrique Guimarães Senna Liberal",
        "username": "phgl",
        "bio": "Programador, fotógrafo e eterno aprendiz",
        "restricao": false,
        "restricao_id": [],
        "ultimo_login": ""
    },
    {
        "id": 3,
        "nome": "Bety Anne de Albuquerque Senna Liberal",
        "username": "basl",
        "bio": "Linda, cheirosa e muito elegante",
        "restricao": false,
        "restricao_id": [],
        "ultimo_login": ""
    }
]